Metadata-Version: 2.1
Name: isbnlib
Version: 3.10.13
Summary: Extract, clean, transform, hyphenate and metadata for ISBNs (International Standard Book Number).
Home-page: https://github.com/xlcnd/isbnlib
Author: Alexandre Lima Conde
Author-email: xlcnd@outlook.com
License: LGPL v3
Download-URL: https://github.com/xlcnd/isbnlib/archive/v3.10.13.zip
Project-URL: Bug Reports, https://github.com/xlcnd/isbnlib/issues
Project-URL: Dev Docs, https://github.com/xlcnd/isbnlib#info
Project-URL: Forum, https://stackoverflow.com/search?tab=newest&q=isbnlib
Project-URL: License, https://github.com/xlcnd/isbnlib/blob/dev/LICENSE-LGPL-3.0.txt
Keywords: ISBN metadata World_Catalogue Google_Books Wikipedia Open_Library BibTeX EndNote RefWorks MSWord opf BibJSON
Platform: any
Classifier: Programming Language :: Python
Classifier: Programming Language :: Python :: 2
Classifier: Programming Language :: Python :: 2.7
Classifier: Programming Language :: Python :: 3
Classifier: Programming Language :: Python :: 3.6
Classifier: Programming Language :: Python :: 3.7
Classifier: Programming Language :: Python :: 3.8
Classifier: Programming Language :: Python :: 3.9
Classifier: Programming Language :: Python :: 3.10
Classifier: Programming Language :: Python :: 3.11
Classifier: License :: OSI Approved :: GNU Lesser General Public License v3 (LGPLv3)
Classifier: Operating System :: OS Independent
Classifier: Development Status :: 5 - Production/Stable
Classifier: Intended Audience :: Developers
Classifier: Topic :: Text Processing :: General
Classifier: Topic :: Software Development :: Libraries :: Python Modules
